arcane/clients.py
arcane_clients-1.5.4.dist-info/METADATA
arcane_clients-1.5.4.dist-info/WHEEL
arcane_clients-1.5.4.dist-info/RECORD
