Metadata-Version: 2.3
Name: arcane-clients
Version: 1.5.4
Summary: Utility functions to interact with our clients_service
Author: Arcane
Author-email: product@wearcane.com
Requires-Python: >=3.6,<4.0
Classifier: Programming Language :: Python :: 3
Classifier: Programming Language :: Python :: 3.6
Classifier: Programming Language :: Python :: 3.7
Classifier: Programming Language :: Python :: 3.8
Classifier: Programming Language :: Python :: 3.9
Classifier: Programming Language :: Python :: 3.10
Classifier: Programming Language :: Python :: 3.11
Classifier: Programming Language :: Python :: 3.12
Classifier: Programming Language :: Python :: 3.13
Requires-Dist: arcane-core (>=1.6,<2.0)
Requires-Dist: arcane-requests (>=0,<1)
Requires-Dist: backoff (>=1.10.0)
Requires-Dist: requests (>=2.23.0,<3.0.0)
